nonebot_plugin_wake_on_lan/__init__.py
nonebot_plugin_wake_on_lan/config.py
nonebot_plugin_wake_on_lan/data.py
nonebot_plugin_wake_on_lan-0.1.6.dist-info/LICENSE
nonebot_plugin_wake_on_lan-0.1.6.dist-info/METADATA
nonebot_plugin_wake_on_lan-0.1.6.dist-info/WHEEL
nonebot_plugin_wake_on_lan-0.1.6.dist-info/RECORD
