Metadata-Version: 2.1
Name: nonebot-plugin-wake-on-lan
Version: 0.1.6
Summary: The Wake-on-LAN plugin for nonebot2
Home-page: https://github.com/tiehu/nonebot-plugin-wake-on-lan
License: MIT
Keywords: nonebot2,wol
Author: tiehu
Requires-Python: >=3.9,<4.0
Classifier: License :: OSI Approved :: MIT License
Classifier: Programming Language :: Python :: 3
Classifier: Programming Language :: Python :: 3.9
Classifier: Programming Language :: Python :: 3.10
Classifier: Programming Language :: Python :: 3.11
Classifier: Programming Language :: Python :: 3.12
Requires-Dist: nonebot2 (>=2.2.0,<3.0.0)
Requires-Dist: pydantic (>=1.10,<2.0)
Project-URL: Repository, https://github.com/tiehu/nonebot-plugin-wake-on-lan
